Metadata-Version: 2.1
Name: ta-clickup
Version: 0.0.1
Summary: A wrapper for the ClickUp API to expedite automations
Home-page: https://www.thoughtfulautomation.com/
Author: Jacob Brooks
Author-email: author@example.com
License: UNKNOWN
Platform: UNKNOWN
Classifier: Programming Language :: Python :: 3
Classifier: Operating System :: OS Independent
Requires-Python: >=3.6
